[{"ProductTitle":"hello","ProductCode":"20","ProductPrice":10,"IsActive":true,"ImageUrl":"/images/buzzcut.png","IsSelected":false},{"ProductTitle":" Cutting","ProductCode":"12000","ProductPrice":0,"IsActive":true,"ImageUrl":"/images/face.png","IsSelected":false},{"ProductTitle":"Pepsi","ProductCode":"2002","ProductPrice":99,"IsActive":true,"ImageUrl":"/images/hair-color.png","IsSelected":false},{"ProductTitle":"test","ProductCode":"21","ProductPrice":12,"IsActive":true,"ImageUrl":"/images/buzzcut.png","IsSelected":false}]